py_zippy-1.0.1.dist-info/licenses/LICENSE
zippy/__init__.py
zippy/cli.py
zippy/create.py
zippy/extract.py
zippy/list.py
zippy/lock.py
zippy/repair.py
zippy/test.py
zippy/unlock.py
zippy/utils.py
py_zippy-1.0.1.dist-info/METADATA
py_zippy-1.0.1.dist-info/WHEEL
py_zippy-1.0.1.dist-info/entry_points.txt
py_zippy-1.0.1.dist-info/top_level.txt
py_zippy-1.0.1.dist-info/RECORD
