Metadata-Version: 2.4
Name: py-zippy
Version: 1.0.1
Summary: Archive Utility Toolkit supporting multi-format workflows, password recovery, and repair helpers.
Author-email: John Hauger Mitander <john@on1.no>
Maintainer-email: John Hauger Mitander <john@on1.no>
License: MIT License
Project-URL: Homepage, https://github.com/John0n1/zippy
Project-URL: Documentation, https://github.com/John0n1/zippy#readme
Project-URL: Repository, https://github.com/John0n1/zippy.git
Project-URL: Issues, https://github.com/John0n1/zippy/issues
Project-URL: Changelog, https://github.com/John0n1/zippy/releases
Keywords: archives,zip,tar,cli,toolkit,compression,encryption,password-recovery
Classifier: Development Status :: 5 - Production/Stable
Classifier: Environment :: Console
Classifier: Intended Audience :: System Administrators
Classifier: Intended Audience :: Developers
Classifier: License :: OSI Approved :: MIT License
Classifier: Operating System :: OS Independent
Classifier: Programming Language :: Python
Classifier: Programming Language :: Python :: 3
Classifier: Programming Language :: Python :: 3.9
Classifier: Programming Language :: Python :: 3.10
Classifier: Programming Language :: Python :: 3.11
Classifier: Programming Language :: Python :: 3.12
Classifier: Programming Language :: Python :: 3.13
Classifier: Topic :: System :: Archiving
Classifier: Topic :: System :: Archiving :: Compression
Classifier: Topic :: Utilities
Requires-Python: >=3.9
License-File: LICENSE
Requires-Dist: colorama>=0.4.6
Requires-Dist: python-dotenv>=1.0
Requires-Dist: pyzipper>=0.3.6
Requires-Dist: patool>=1.12
Provides-Extra: dev
Requires-Dist: pytest>=7.0; extra == "dev"
Requires-Dist: pytest-cov>=4.0; extra == "dev"
Requires-Dist: black>=23.0; extra == "dev"
Requires-Dist: ruff>=0.1.0; extra == "dev"
Provides-Extra: full
Requires-Dist: py7zr>=0.20.0; extra == "full"
Requires-Dist: rarfile>=4.0; extra == "full"
Provides-Extra: windows
Requires-Dist: pyinstaller>=5.0; extra == "windows"
Provides-Extra: macos
Requires-Dist: py2app>=0.28; extra == "macos"
Dynamic: license-file
